uniondiff/__init__.py
uniondiff/__main__.py
uniondiff/_version.py
uniondiff/cli.py
uniondiff/differ.py
uniondiff/exceptions.py
uniondiff/filelib.py
uniondiff/filelib_tar.py
uniondiff/osshim.py
uniondiff/output.py
uniondiff/output_aufs.py
uniondiff/output_file.py
uniondiff/output_overlay.py
uniondiff/output_tar.py
uniondiff-0.1.1.dist-info/LICENSE
uniondiff-0.1.1.dist-info/METADATA
uniondiff-0.1.1.dist-info/WHEEL
uniondiff-0.1.1.dist-info/entry_points.txt
uniondiff-0.1.1.dist-info/top_level.txt
uniondiff-0.1.1.dist-info/RECORD
