Metadata-Version: 2.1
Name: uniondiff
Version: 0.1.1
Summary: Directory difference CLI tool
Home-page: http://github.com/msg555/uniondiff/
Author: Mark Gordon
Author-email: msg555@gmail.com
Classifier: Programming Language :: Python
Classifier: Programming Language :: Python :: 3
Classifier: Programming Language :: Python :: 3.8
Classifier: Programming Language :: Python :: 3.9
Classifier: Programming Language :: Python :: 3.10
Classifier: Programming Language :: Python :: 3.11
Classifier: Programming Language :: Python :: 3.12
Classifier: License :: OSI Approved :: BSD License
Classifier: Operating System :: OS Independent
Requires-Python: >=3.8
License-File: LICENSE
